[{"id":1,"tokenList":[{"amount":64,"buyAvgPrice":10.18,"cryptoHoldings":438.4,"cryptocurrencyId":"polkadot","priceChangePercentage24h":-3.22637,"name":"Polkadot","symbol":"DOT","historyList":[{"name":"Polkadot","cryptocurrencyId":"polkadot","amount":64,"type":"Buy","symbol":"DOT","price":10.18,"timestamp":1648825637077,"id":141916535794542660}],"image":"https://assets.coingecko.com/coins/images/12171/large/polkadot.png?1639712644","currentPrice":6.85},{"amount":496,"buyAvgPrice":0.5143915,"cryptoHoldings":226.140288,"cryptocurrencyId":"cardano","priceChangePercentage24h":-3.72738,"name":"Cardano","symbol":"ADA","historyList":[{"name":"Cardano","cryptocurrencyId":"cardano","amount":100,"type":"Buy","symbol":"ADA","price":0.515913,"timestamp":1653389621286,"id":106975997803477340},{"name":"Cardano","cryptocurrencyId":"cardano","amount":1000,"type":"Buy","symbol":"ADA","price":0.51287,"timestamp":1653395593893,"id":95915182541483360},{"cryptocurrencyId":"cardano","amount":-100,"price":0.518409,"name":"Cardano","symbol":"ADA","timestamp":1653504058814,"type":"Sell","id":62278290411750080},{"cryptocurrencyId":"cardano","amount":-504,"price":0.518409,"name":"Cardano","symbol":"ADA","timestamp":1653504080659,"type":"Sell","id":156668661505842140}],"image":"https://assets.coingecko.com/coins/images/975/large/cardano.png?1547034860","currentPrice":0.455928}]}]